custom_app/__init__.py
custom_app/cli.py
custom_app_momo-4.3.3.dist-info/METADATA
custom_app_momo-4.3.3.dist-info/WHEEL
custom_app_momo-4.3.3.dist-info/entry_points.txt
custom_app_momo-4.3.3.dist-info/top_level.txt
custom_app_momo-4.3.3.dist-info/RECORD
