Metadata-Version: 2.4
Name: custom-app-momo
Version: 4.3.3
Summary: Générateur de structure d'app Django personnalisée
Author: Mohamed
Author-email: omomo9414@gmail.com
License: MIT
Classifier: Programming Language :: Python :: 3
Classifier: Framework :: Django
Classifier: License :: OSI Approved :: MIT License
Dynamic: author
Dynamic: author-email
Dynamic: classifier
Dynamic: description
Dynamic: description-content-type
Dynamic: license
Dynamic: summary
